Workbook

Sheet Hoja de datos
B36: Rúbrica de evaluación laboratorio 2
B37: Criterio | C37: Puntos | D37: Excelente (90–100%) | E37: Bueno (70–89%) | F37: Básico (50–69%) | G37: Insuficiente (0–49%) | H37: Nota
B38: 1. Razón de Liquidez | D38: Fórmula identificada y datos seleccionados correctamente; operación matemática correcta; resultado presentado con unidad/veces; interpretación coherente. Cumple de forma completa y sin errores relevantes. | E38: Fórmula identificada y datos seleccionados correctamente; operación matemática correcta; resultado presentado con unidad/veces; interpretación coherente. Presenta uno o dos errores menores que no afectan sustancialmente el resultado. | F38: Fórmula identificada y datos seleccionados correctamente; operación matemática correcta; resultado presentado con unidad/veces; interpretación coherente. Cumple parcialmente; presenta errores de procedimiento, datos o interpretación que afectan el resultado. | G38: Fórmula identificada y datos seleccionados correctamente; operación matemática correcta; resultado presentado con unidad/veces; interpretación coherente. No desarrolla el criterio, presenta errores sustanciales o el resultado no es verificable.
C39: 10 | H39: 0
B40: 2. Rotación de Activos Totales, Rendimiento sobre los activos ROA , Rendimiento sobre el capital contable ROE | D40: Ventas/ingresos y activos totales correctamente identificados; cálculo correcto; resultado en veces; interpretación coherente. Cumple de forma completa y sin errores relevantes. | E40: Ventas/ingresos y activos totales correctamente identificados; cálculo correcto; resultado en veces; interpretación coherente. Presenta uno o dos errores menores que no afectan sustancialmente el resultado. | F40: Ventas/ingresos y activos totales correctamente identificados; cálculo correcto; resultado en veces; interpretación coherente. Cumple parcialmente; presenta errores de procedimiento, datos o interpretación que afectan el resultado. | G40: Ventas/ingresos y activos totales correctamente identificados; cálculo correcto; resultado en veces; interpretación coherente. No desarrolla el criterio, presenta errores sustanciales o el resultado no es verificable.
C41: 10 | H41: 0
B42: 3. Prueba Ácida | D42: Fórmula aplicada excluyendo inventarios (y considerando las partidas pertinentes); cálculo correcto; resultado presentado; interpretación coherente. Cumple de forma completa y sin errores relevantes. | E42: Fórmula aplicada excluyendo inventarios (y considerando las partidas pertinentes); cálculo correcto; resultado presentado; interpretación coherente. Presenta uno o dos errores menores que no afectan sustancialmente el resultado. | F42: Fórmula aplicada excluyendo inventarios (y considerando las partidas pertinentes); cálculo correcto; resultado presentado; interpretación coherente. Cumple parcialmente; presenta errores de procedimiento, datos o interpretación que afectan el resultado. | G42: Fórmula aplicada excluyendo inventarios (y considerando las partidas pertinentes); cálculo correcto; resultado presentado; interpretación coherente. No desarrolla el criterio, presenta errores sustanciales o el resultado no es verificable.
C44: 10 | H44: 0
B45: 4. Margen de Utilidad Operativa | D45: Utilidad operativa e ingresos/ventas correctamente identificados; cálculo porcentual correcto; interpretación coherente. Cumple de forma completa y sin errores relevantes. | E45: Utilidad operativa e ingresos/ventas correctamente identificados; cálculo porcentual correcto; interpretación coherente. Presenta uno o dos errores menores que no afectan sustancialmente el resultado. | F45: Utilidad operativa e ingresos/ventas correctamente identificados; cálculo porcentual correcto; interpretación coherente. Cumple parcialmente; presenta errores de procedimiento, datos o interpretación que afectan el resultado. | G45: Utilidad operativa e ingresos/ventas correctamente identificados; cálculo porcentual correcto; interpretación coherente. No desarrolla el criterio, presenta errores sustanciales o el resultado no es verificable.
C46: 10 | H46: 0
B47: 5. Rotación de Inventario | D47: Costo de ventas e inventario correctamente identificados; cálculo correcto; resultado en veces; interpretación coherente. Cumple de forma completa y sin errores relevantes. | E47: Costo de ventas e inventario correctamente identificados; cálculo correcto; resultado en veces; interpretación coherente. Presenta uno o dos errores menores que no afectan sustancialmente el resultado. | F47: Costo de ventas e inventario correctamente identificados; cálculo correcto; resultado en veces; interpretación coherente. Cumple parcialmente; presenta errores de procedimiento, datos o interpretación que afectan el resultado. | G47: Costo de ventas e inventario correctamente identificados; cálculo correcto; resultado en veces; interpretación coherente. No desarrolla el criterio, presenta errores sustanciales o el resultado no es verificable.
C48: 10 | H48: 0
B49: 6. Índice de Endeudamiento, apalancamiento financiero | D49: Pasivo total y activo total correctamente identificados; cálculo porcentual correcto; interpretación coherente. Cumple de forma completa y sin errores relevantes. | E49: Pasivo total y activo total correctamente identificados; cálculo porcentual correcto; interpretación coherente. Presenta uno o dos errores menores que no afectan sustancialmente el resultado. | F49: Pasivo total y activo total correctamente identificados; cálculo porcentual correcto; interpretación coherente. Cumple parcialmente; presenta errores de procedimiento, datos o interpretación que afectan el resultado. | G49: Pasivo total y activo total correctamente identificados; cálculo porcentual correcto; interpretación coherente. No desarrolla el criterio, presenta errores sustanciales o el resultado no es verificable.
C50: 10 | H50: 0
B51: 7. Periodo de Cobro y pago | D51: Cuentas por cobrar y ventas/ingresos correctamente identificados; fórmula y base temporal coherentes; cálculo correcto; resultado en días; interpretación coherente. Cumple de forma completa y sin errores relevantes. | E51: Cuentas por cobrar y ventas/ingresos correctamente identificados; fórmula y base temporal coherentes; cálculo correcto; resultado en días; interpretación coherente. Presenta uno o dos errores menores que no afectan sustancialmente el resultado. | F51: Cuentas por cobrar y ventas/ingresos correctamente identificados; fórmula y base temporal coherentes; cálculo correcto; resultado en días; interpretación coherente. Cumple parcialmente; presenta errores de procedimiento, datos o interpretación que afectan el resultado. | G51: Cuentas por cobrar y ventas/ingresos correctamente identificados; fórmula y base temporal coherentes; cálculo correcto; resultado en días; interpretación coherente. No desarrolla el criterio, presenta errores sustanciales o el resultado no es verificable.
C52: 10 | H52: 0
B53: 8. Explicación / análisis integral | D53: Explica los 7 resultados, relaciona cada indicador con la situación financiera, identifica fortalezas/riesgos y sustenta conclusiones con los resultados calculados. Cumple de forma completa y sin errores relevantes. | E53: Explica los 7 resultados, relaciona cada indicador con la situación financiera, identifica fortalezas/riesgos y sustenta conclusiones con los resultados calculados. Presenta uno o dos errores menores que no afectan sustancialmente el resultado. | F53: Explica los 7 resultados, relaciona cada indicador con la situación financiera, identifica fortalezas/riesgos y sustenta conclusiones con los resultados calculados. Cumple parcialmente; presenta errores de procedimiento, datos o interpretación que afectan el resultado. | G53: Explica los 7 resultados, relaciona cada indicador con la situación financiera, identifica fortalezas/riesgos y sustenta conclusiones con los resultados calculados. No desarrolla el criterio, presenta errores sustanciales o el resultado no es verificable.
C54: 15 | H54: 0
B55: 9. Presentación y procedimiento | D55: Procedimiento ordenado y legible; datos/fórmulas identificables; operaciones trazables; resultados claramente diferenciados; entrega completa. Cumple de forma completa y sin errores relevantes. | E55: Procedimiento ordenado y legible; datos/fórmulas identificables; operaciones trazables; resultados claramente diferenciados; entrega completa. Presenta uno o dos errores menores que no afectan sustancialmente el resultado. | F55: Procedimiento ordenado y legible; datos/fórmulas identificables; operaciones trazables; resultados claramente diferenciados; entrega completa. Cumple parcialmente; presenta errores de procedimiento, datos o interpretación que afectan el resultado. | G55: Procedimiento ordenado y legible; datos/fórmulas identificables; operaciones trazables; resultados claramente diferenciados; entrega completa. No desarrolla el criterio, presenta errores sustanciales o el resultado no es verificable.
C56: 15 | H56: 0
B57: NOTA FINAL | H57: 0
B60: NOTA: TODAS LAS NOTA A COLOCAR DEBEN DE ESTAR ENTRE 0 Y 10
B61: Por ejemplo, si usted cree que la nota de explicación y análisis integral es de 6, usted debe de colocar 10, en el rango de porcentaje del 69%

Sheet Planteamiento EJ 1 Y 2
A2: Ejercicio 1 y 2 de Análisis Financiero: Se presentan los Estados Financieros de la empresa "ABC SA de CV": Balance General y Estado de Resultados de los años 2025 y 2024
A3: VASQUEZ MENJIVAR, LUIS ENRIQUE - VM15037
A4: Se requiere calcular y analizar, para cada año los sigueintes indicadores:
A5: Indicadores o ratios: | B5: Resultado | D5: FORMULAS USADAS | E5: Notas
B6: 2025 | C6: 2024
A7: 1. Solvencia o ratio de liquidez | B7: ='Estados Financ EJ 1 Y 2'!B12/'Estados Financ EJ 1 Y 2'!B30 -> 1.2915699 | C7: ='Estados Financ EJ 1 Y 2'!C12/'Estados Financ EJ 1 Y 2'!C30 -> 1.4158122 | D7: Activos Corrientes / Pasivos Corrientes.
A8: 2. Prueba Acida | B8: =('Estados Financ EJ 1 Y 2'!B12-'Estados Financ EJ 1 Y 2'!B10)/'Estados Financ EJ 1 Y 2'!B30 -> 0.7023588 | C8: =('Estados Financ EJ 1 Y 2'!C12-'Estados Financ EJ 1 Y 2'!C10)/'Estados Financ EJ 1 Y 2'!C30 -> 0.97242056 | D8: (Activos Corrientes - Inventario) / Pasivos Corrientes.
A9: 3. Capital de trabajo | B9: ='Estados Financ EJ 1 Y 2'!B12-'Estados Financ EJ 1 Y 2'!B30 -> 2535523 | C9: ='Estados Financ EJ 1 Y 2'!C12-'Estados Financ EJ 1 Y 2'!C30 -> 2540275 | D9: Activo Corriente - Pasivo Corriente
A10: 4. Rotación de inventarios | B10: ='Estados Financ EJ 1 Y 2'!I7/'Estados Financ EJ 1 Y 2'!B10 -> 3.8010253 | C10: ='Estados Financ EJ 1 Y 2'!J7/'Estados Financ EJ 1 Y 2'!C10 -> 7.3274281 | D10: Costo de los Bienes Vendidos / Inventario
A11: 5. Periodo promedio de cobranza | B11: ='Estados Financ EJ 1 Y 2'!B9/('Estados Financ EJ 1 Y 2'!I6/365) -> 77.912468 | C11: ='Estados Financ EJ 1 Y 2'!C9/('Estados Financ EJ 1 Y 2'!J6/365) -> 75.095392 | D11: Cuentas por cobrar / (Ingreso por ventas anuales / 365)
A12: 6. Periodo promedio de pago | B12: =('Estados Financ EJ 1 Y 2'!B26+'Estados Financ EJ 1 Y 2'!B27)/('Estados Financ EJ 1 Y 2'!I7/365) -> 76.289514 | C12: =('Estados Financ EJ 1 Y 2'!C26+'Estados Financ EJ 1 Y 2'!C27)/('Estados Financ EJ 1 Y 2'!J7/365) -> 46.238139 | D12: Cuentas por pagar / (Ingreso por compras anuales / 365) | E12: Cuentas por pagar se utilizan proveedores nacionales e internacionales
A13: 7. Apalancamiento financero | B13: ='Estados Financ EJ 1 Y 2'!B37/'Estados Financ EJ 1 Y 2'!B43 -> 1.541967 | C13: ='Estados Financ EJ 1 Y 2'!C37/'Estados Financ EJ 1 Y 2'!C43 -> 1.4309576 | D13: Total Pasivo / Total Patrimonio
A14: 8. Razón de endeudamiento | B14: ='Estados Financ EJ 1 Y 2'!B37/'Estados Financ EJ 1 Y 2'!B18 -> 0.60660386 | C14: ='Estados Financ EJ 1 Y 2'!C37/'Estados Financ EJ 1 Y 2'!C18 -> 0.58863947 | D14: Total de pasivos / Total de activos
A15: 9. Rendimiento sobre los activos ROA | B15: ='Estados Financ EJ 1 Y 2'!I20/'Estados Financ EJ 1 Y 2'!B18 -> 0.021645724 | C15: ='Estados Financ EJ 1 Y 2'!J20/'Estados Financ EJ 1 Y 2'!C18 -> 0.018361451 | D15: Utilidad Neta / Total de activos
A16: 10. Rendimiento sobre el capital contable ROE | B16: ='Estados Financ EJ 1 Y 2'!I20/'Estados Financ EJ 1 Y 2'!B43 -> 0.055022715 | C16: ='Estados Financ EJ 1 Y 2'!J20/'Estados Financ EJ 1 Y 2'!C43 -> 0.044635908 | D16: Utilidad neta / Patrimonio
A17: 11. Margen de Utilidad Neta | B17: ='Estados Financ EJ 1 Y 2'!I20/'Estados Financ EJ 1 Y 2'!I6 -> 0.018415193 | C17: ='Estados Financ EJ 1 Y 2'!J20/'Estados Financ EJ 1 Y 2'!J6 -> 0.014121927 | D17: Utilidad Neta / Ventas
A18: 12. Año más rentable | B18: 2025 | E18: En el 2025 los márgenes de utilidad (1.84%), el ROA (2.16%) y el ROE (5.50%) superan los resultados de 2024. La empresa logró generar mayores ganancias en proporción a sus ventas y activos.
A19: 13.Año con negocio más equilibrado y seguro | C19: 2024 | E19: En 2024 la liquidez es superior (1.42), la prueba ácida roza el 1.0 (0.97), el nivel de endeudamiento es menor (58.86%) y el inventario rota mucho más rápido. En 2025, el exceso de inventario redujo la liquidez inmediata (prueba ácida de 0.70).

Sheet Estados Financ EJ 1 Y 2
A2: BALANCE GENERAL ABC SA de CV | H2: ESTADO DE RESULTADOS EMPRESA ABC SA de CV
A3: 31 diciembre del 2025 y 2024 | H3: Al 31 de diciembre 2025 y 2024
B5: 2025 | C5: 2024 | I5: 2025 | J5: 2024
A6: ACTIVO | H6: Ventas (Ventas a Crédito) | I6: 23829346 | J6: 23820900
A7: Activo Circulante (Corriente): | H7: Costo de Ventas | I7: 19475857 | J7: 19848266
A8: Efectivo | B8: 595173 | C8: 613050 | H8: Utilidad bruta | I8: =I6-I7 -> 4353489 | J8: =J6-J7 -> 3972634
A9: Cuentas y documentos por cobrar | B9: 5086584 | C9: 4900931
A10: Inventarios | B10: 5123843 | C10: 2708763 | H10: Gastos de operación:
A11: Gastos pagados por anticipado | B11: 426031 | C11: 426719 | H11: Gastos de administración | I11: 1140950 | J11: 1040242
A12: Total del activo circulante | B12: =SUM(B8:B11) -> 11231631 | C12: =SUM(C8:C11) -> 8649463 | H12: Gastos de ventas | I12: 2239379 | J12: 2107973
H13: Gastos financieros | I13: 509437 | J13: 532312
A14: Activo No Circulante: | H14: Total gasto de operación | I14: =SUM(I11:I13) -> 3889766 | J14: =SUM(J11:J13) -> 3680527
A15: Inversiones | B15: 3754 | C15: 3754
A16: Maquinaria, mobiliario y equipo netos (nota 7) | B16: 8227209 | C16: 8766377 | H16: Utilidad de operación | I16: 463723 | J16: 292107
A17: Otros activos - netos (nota 8) | B17: 810325 | C17: 901235 | H17: Otros ingresos netos | I17: 8485 | J17: 44290
A18: Total del Activo | B18: =B12+B15+B16+B17 -> 20272919 | C18: =C12+C15+C16+C17 -> 18320829 | H18: Utilidad antes de impuesto sobre la renta | I18: =SUM(I16:I17) -> 472208 | J18: =SUM(J16:J17) -> 336397
H19: Impuesto sobre la rentas | I19: 33386 | J19: 0
A20: PASIVO Y PATRIMONIO | H20: Utilidad Neta | I20: =I18-I19 -> 438822 | J20: =J18-J19 -> 336397
A21: Pasivo Circulante (Corriente):
A22: Sobregiros bancarios | B22: 0 | C22: 303815
A23: Vencimiento circulante de préstamos a largo plazo | B23: 1021851 | C23: 685615
A24: Vencimiento circulante de documentos por pagar | B24: 24948 | C24: 49900
A25: Préstamos bancarios a corto plazo | B25: 2875811 | C25: 1973876
A26: Proveedores nacionales | B26: 331826 | C26: 386634
A27: Proveedores del exterior | B27: 3738869 | C27: 2127741
A28: Cuentas por pagar a compañías relacionadas | B28: 86634 | C28: 21384
A29: Otras cuentas por pagar y gastos acumulados | B29: 616169 | C29: 560223
A30: Total del pasivo circulante | B30: =SUM(B22:B29) -> 8696108 | C30: =SUM(C22:C29) -> 6109188
A32: Pasivo a Largo Plazo:
A33: Préstamos a largo plazo menos vencimiento circulante | B33: 3597478 | C33: 4647788
A34: Documentos por pagar menos vencimiento circulante | B34: 0 | C34: 25603
A35: Provisión para obligaciones laborales | B35: 1143 | C35: 1143
A36: Otros pasivos | B36: 2902 | C36: 641
A37: Total del pasivo | B37: =B30+B33+B34+B35+B36 -> 12297631 | C37: =C30+C33+C34+C35+C36 -> 10784363
A39: Patrimonio:
A40: Capital social - 462,000 acciones comunes | B40: 5280000 | C40: 5280000
A41: Reserva legal (nota 16) | B41: 956497 | C41: 923443
A42: Utilidades disponibles (nota 16) | B42: 1738791 | C42: 1333023
A43: Total del patrimonio | B43: 7975288 | C43: 7536466
A45: Total Pasivo y Patrimonio | B45: =B37+B43 -> 20272919 | C45: =C37+C43 -> 18320829

Sheet Estad Financi EJ 3
A2: EJERCICIO 3: Cálculo de razones financieras
A3: BALANCE GENERAL EMPRESA AZUCARERA | H3: ESTADO DE RESULTADOS EMPRESA AZUCARERA DEL 01 DE ENERO AL 31 DE DICIEMBRE 2022
A4: Al 31 diciembre 2023
I5: Ingresos de Operación | J5: 420000
A6: Activo Corriente | D6: Pasivos | H6: (-) | I6: Costo de Venta | J6: 197400
A7: Efectivo y Equivalentes | B7: 110824.86 | D7: Cuentas por pagar Comerciales | E7: 13075.7 | I7: Utilidad Bruta | J7: =J5-J6 -> 222600
A8: Cuentas por Cobrar | B8: 33840 | D8: Retenciones por Pagar | E8: 1236.3 | I8: Gastos Operativos | J8: =J9+J10+J11 -> 124900
A9: Estimacion Ctas Incobrables | B9: -1690.47 | D9: Obligaciones por Beneficios a empleados | E9: 1128.66 | H9: (-) | I9: Gastos de Admon | J9: 61671.1
A10: Inventarios | B10: 63250 | D10: Impuestos por pagar | E10: 23126.3 | H10: (-) | I10: Gastos de Venta | J10: 61802.27
A11: Total de Activo Corriente | B11: =SUM(B7:B10) -> 206224.39 | D11: Total de Pasivo Corriente | E11: =SUM(E7:E10) -> 38566.96 | H11: (-) | I11: Gastos Financieros | J11: 1426.63
D12: Pasivo no Corriente | I12: Utilidad del Ejercicio antes de R.L | J12: =J7-J8 -> 97700
A13: Activo no Corriente | D13: Prestamos a Largo Plazo | E13: 12000 | H13: (-) | I13: Reserva Legal | J13: =J12*0.07 -> 6839
A14: Propiedad, Planta y Equipo | B14: 205000 | D14: Provision para obligaciones Laborales | E14: 3309.53 | I14: Utilidad del Ejercicio antes de R.L | J14: =J12-J13 -> 90861
A15: Depreciacion Acumulada | B15: -20500 | D15: Total de Pasivo no Corriente | E15: =SUM(E13:E14) -> 15309.53 | H15: (-) | I15: Gastos por Impuesto | J15: =27258.3-450+450 -> 27258.3
A16: Activo por Impuesto Diferido | B16: 1500 | D16: TOTAL PASIVOS | E16: =E11+E15 -> 53876.49
D17: Patrimonio
D18: Capital Social | E18: 250000
A19: Total de Activo no Corriente | B19: =B14+B15+B16+B17+B18 -> 186000 | D19: Reserva | E19: 24745.2
D20: Utilidad del Ejercicio | E20: 63602.7
D21: Total Patrimonio | E21: =SUM(E18:E20) -> 338347.9
A22: Total Activos | B22: =B11+B19 -> 392224.39 | D22: Total Pasivo mas Patrimonio | E22: =E16+E21 -> 392224.39
A25: VASQUEZ MENJIVAR, LUIS ENRIQUE - VM15037
A26: Calcular:
A27: Razón Financiera | B27: Respuesta | C27: Formula
A28: Razon de Liquidez | B28: =B11/E11 -> 5.3471777 | C28: Activos Corrientes / Pasivos Corrientes.
A29: Prueba ácida | B29: =(B11-B10)/E11 -> 3.7071729 | C29: (Activos Corrientes - Inventarios) / Pasivos Corrientes
A30: Rotacion de Activos Totales | B30: =J5/B22 -> 1.0708156 | C30: Ingreso por ventas / Total de activos
A31: Rotación de Inventario | B31: =J6/B10 -> 3.1209486 | C31: Costo de los Bienes Vendidos / Inventario
A32: Indice de endeudamiento | B32: =E16/B22 -> 0.1373614 | C32: Total de pasivos / Total de activos

Sheet Hoja2
