Workbook

Sheet Portada
B3: #VALUE! | J3: #VALUE!
F5: Unidad II
F11: Administración de planillas

Sheet Planteamiento
A1: #VALUE! | D1: Formato para desarrollo de ejercicios | G1: Formato: FPDE
G2: Fecha de revisión: 2024 / febrero
G3: Fecha de creación: 2024 / febrero
A5: Tema | B5: : | C5: Provisión de planilla
A6: Tipo de prueba | B6: : | C6: Ejercicio práctico
A7: Objetivo | B7: : | C7: Desarrollar una provisión de planilla con el fin de poder visionar el costo de las áreas a cargo.
A8: Link | B8: :
A10: Planteamiento del problema:
C12: En la tabla N ° 1 se puede observar el detalle de la planilla a cancelar en el mes de diciembre. Con la información brindada determine:
B14: #VALUE! | C14: El monto total de las horas extras dirunas, nocturnas
B16: #VALUE! | C16: El monto total de la nocturnidad
B18: #VALUE! | C18: El monto de pago de vacaciones para quien aplique.
B20: #VALUE! | C20: El monto del pago del aguinaldo para quien aplique. (Considere un aguinaldo gravado sobre el exceso de $ 1,200 / mes)
B22: #VALUE! | C22: El monto del aguinaldo no gravado
B24: #VALUE! | C24: El monto del aguinaldo gravado
B26: #VALUE! | C26: Considerando un viático por $ 30 por empleado en concepto de alimentación, calcular el monto gravado cotizable
B28: #VALUE! | C28: Las prestacion del ISSS a pagar por el empleado y el patrono.
B30: #VALUE! | C30: Las prestacion del AFP´S a pagar por el empleado y el patrono.
B32: #VALUE! | C32: Las prestacion del ISSS a pagar por el empleado y el patrono.
B34: #VALUE! | C34: El monto a depositar del empleado.
B36: #VALUE! | C36: El monto a depositar a la planilla única.
D39: Tabla N ° 1 | E39: Planilla de bodega
C41: N° | D41: AREA | E41: Codigo | F41: PUESTO FUNCIONAL | G41: Fecha de ingreso a la empresa | H41: Fecha de corte | I41: Tiempo en la empresa (años) | J41: TOTAL POR PUESTO/ MENSUAL | K41: Horas extras diurnas (hrs /mes) | L41: Horas extras nocturnas (hrs /mes) | M41: Horas nocturnas (hrs /mes) | N41: Subsidio por alimentación para el siguiente mes
C42: 1 | D42: Gerencia | E42: JF | F42: Jefe de Operaciones | G42: 39447 | H42: 45355 | I42: =(H42-G42)/365 -> 16.186301 | J42: 1500 | K42: 0 | L42: 0 | M42: 0 | N42: 30
C43: =1+C42 -> 2 | D43: Administración | E43: AJCD | F43: Asistente de JCD | G43: 42037 | H43: 45382 | I43: =(H43-G43)/365 -> 9.1643836 | J43: 450 | K43: 0 | L43: 0 | M43: 0 | N43: 30
C44: =1+C43 -> 3 | D44: IT | E44: SR | F44: Soporte de redes y HW | G44: 43437 | H44: =+H43 -> 45382 | I44: =(H44-G44)/365 -> 5.3287671 | J44: 800 | K44: 0 | L44: 0 | M44: 0 | N44: 30
C45: =1+C44 -> 4 | D45: Contaduría | E45: CG | F45: Contador General | G45: 44046 | H45: =+H44 -> 45382 | I45: =(H45-G45)/365 -> 3.660274 | J45: 800 | K45: 0 | L45: 0 | M45: 0 | N45: 30
I46: SUB-TOTAL | J46: =SUM(J42:J45) -> 3550
C47: =+C45+1 -> 5 | D47: Bodega | E47: JB | F47: Jefe de bodega | G47: 43655 | H47: =+H45 -> 45382 | I47: =(H47-G47)/365 -> 4.7315068 | J47: 650 | K47: 45 | L47: 25 | M47: =39*2 -> 78 | N47: 30
C48: =+C47+1 -> 6 | D48: Bodega | E48: AUX01 | F48: Auxiliares de bodega01 | G48: 41883 | H48: =+H47 -> 45382 | I48: =(H48-G48)/365 -> 9.5863014 | J48: 435 | K48: 65 | L48: 5 | M48: 14 | N48: 30
C49: =+C48+1 -> 7 | D49: Bodega | E49: AUX02 | F49: Auxiliares de bodega02 | G49: 44197 | H49: =+H48 -> 45382 | I49: =(H49-G49)/365 -> 3.2465753 | J49: 390 | K49: 35 | L49: 25 | M49: 78 | N49: 30
C50: =+C49+1 -> 8 | D50: Bodega | E50: AUX03 | F50: Auxiliares de bodega03 | G50: 44896 | H50: =+H49 -> 45382 | I50: =(H50-G50)/365 -> 1.3315068 | J50: 365 | K50: 25 | L50: 35 | M50: 39 | N50: 30
C51: =+C50+1 -> 9 | D51: Bodega | E51: AUX04 | F51: Auxiliares de bodega04 | G51: 43815 | H51: =+H50 -> 45382 | I51: =(H51-G51)/365 -> 4.2931507 | J51: 415 | K51: 12 | L51: 20 | M51: 39 | N51: 30
C52: =+C51+1 -> 10 | D52: Bodega | E52: MONT | F52: Montacarguista | G52: 43435 | H52: =+H47 -> 45382 | I52: =(H52-G52)/365 -> 5.3342466 | J52: 450 | K52: 19 | L52: 25 | M52: =39*4 -> 156 | N52: 30
C53: =+C52+1 -> 11 | D53: Bodega | E53: REV | F53: Revisador | G53: 45170 | H53: =+H48 -> 45382 | I53: =(H53-G53)/365 -> 0.58082192 | J53: 425 | K53: 44 | L53: 33 | M53: 0 | N53: 30
I54: SUB-TOTAL | J54: =SUM(J47:J53) -> 3130
I55: TOTAL | J55: =+J46+J54 -> 6680

Sheet PLANILLA
E1: 45657 | F1: =MONTH(E1) -> 12
E3: Tabla N ° 1 | F3: Planilla de bodega
U4: 0.075 | V4: 0.03 | W4: 0.0875 | X4: 0.0725 | Y4: 0.075 | Z4: 0.0875 | AD4: No tocar
B5: Pago de planilla
A6: N° | B6: AREA | C6: Codigo | D6: PUESTO FUNCIONAL | E6: Fecha de ingreso a la empresa | F6: Fecha de corte | G6: Tiempo en la empresa (años) | H6: TOTAL POR PUESTO/ MENSUAL | I6: Horas extras diurnas (hrs /mes) | J6: Horas extras nocturnas (hrs /mes) | K6: Horas nocturnas (hrs /mes) | L6: Subsidio por alimentación para el siguiente mes | M6: Horas extras diurnas ($ /mes) | N6: Horas extras nocturnas ($ /mes) | O6: Horas nocturnas ($ /mes) | P6: Vaciones | Q6: Aguinaldo total | R6: Aguinaldo no gravado | S6: Aguinaldo gravado para renta | T6: Monto gravado cotizable | U6: ISSS Patronal ( 7.5 % ) / mes | V6: ISSS Empleado ( 3.0 % ) / mes | W6: AFPS Patronal (8.75 %) / mes | X6: AFPS Empleado (7.25 %) / mes | Y6: Monto a depositar al empleado | Z6: Monto a depositar en la planilla única | AD6: Total de horas extras
A7: 1 | B7: Gerencia | C7: JF | D7: Jefe de Operaciones | E7: 39447 | F7: 46022 | G7: =(F7-E7)/365 -> 18.013699 | H7: 1500 | I7: 0 | J7: 0 | K7: 0 | L7: 30 | R7: =+Q7-S7 -> 0 | S7: =IF(Q7>=1200,(Q7-1200),0) -> 0 | AD7: =+M7+N7 -> 0
A8: =1+A7 -> 2 | B8: Administración | C8: AJCD | D8: Asistente de JCD | E8: 42037 | F8: 46022 | G8: =(F8-E8)/365 -> 10.917808 | H8: 450 | I8: 0 | J8: 0 | K8: 0 | L8: 30 | R8: =+Q8-S8 -> 0 | S8: =IF(Q8>=1200,(1200-Q8),0) -> 0 | AD8: =+M8+N8 -> 0
A9: =1+A8 -> 3 | B9: IT | C9: SR | D9: Soporte de redes y HW | E9: 43437 | F9: 46022 | G9: =(F9-E9)/365 -> 7.0821918 | H9: 900 | I9: 0 | J9: 0 | K9: 0 | L9: 30 | R9: =+Q9-S9 -> 0 | S9: =IF(Q9>=1200,(1200-Q9),0) -> 0 | AD9: =+M9+N9 -> 0
A10: =1+A9 -> 4 | B10: Contabilidad | C10: CG | D10: Contador General | E10: 44046 | F10: 46022 | G10: =(F10-E10)/365 -> 5.4136986 | H10: 1100 | I10: 0 | J10: 0 | K10: 0 | L10: 30 | R10: =+Q10-S10 -> 0 | S10: =IF(Q10>=1200,(1200-Q10),0) -> 0 | AD10: =+M10+N10 -> 0
G11: SUB-TOTAL | H11: =SUM(H7:H10) -> 3950 | M11: =SUM(M7:M10) -> 0 | N11: =SUM(N7:N10) -> 0 | O11: =SUM(O7:O10) -> 0 | P11: =SUM(P7:P10) -> 0 | Q11: =SUM(Q7:Q10) -> 0 | R11: =SUM(R7:R10) -> 0 | S11: =SUM(S7:S10) -> 0 | T11: =SUM(T7:T10) -> 0 | ... Z11: =SUM(Z7:Z10) -> 0 | AD11: =+M11+N11 -> 0
A12: =+A10+1 -> 5 | B12: Bodega | C12: JB | D12: Jefe de bodega | E12: 43655 | F12: =+F10 -> 46022 | G12: =(F12-E12)/365 -> 6.4849315 | H12: 650 | I12: 45 | J12: 25 | K12: =39*2 -> 78 | L12: 30 | R12: =+Q12-S12 -> 0 | S12: =IF(Q12>=1200,(1200-Q12),0) -> 0 | Z12: =+U12+V12+W12+X12 -> 0 | AD12: =+M12+N12 -> 0
A13: =+A12+1 -> 6 | B13: Bodega | C13: AUX01 | D13: Auxiliares de bodega01 | E13: 41883 | F13: =+F12 -> 46022 | G13: =(F13-E13)/365 -> 11.339726 | H13: 435 | I13: 65 | J13: 5 | K13: 14 | L13: 30 | R13: =+Q13-S13 -> 0 | S13: =IF(Q13>=1200,(1200-Q13),0) -> 0 | Z13: =+U13+V13+W13+X13 -> 0 | AD13: =+M13+N13 -> 0
A14: =+A13+1 -> 7 | B14: Bodega | C14: AUX02 | D14: Auxiliares de bodega02 | E14: 44197 | F14: =+F13 -> 46022 | G14: =(F14-E14)/365 -> 5 | H14: 390 | I14: 35 | J14: 25 | K14: 78 | L14: 30 | R14: =+Q14-S14 -> 0 | S14: =IF(Q14>=1200,(1200-Q14),0) -> 0 | Z14: =+U14+V14+W14+X14 -> 0 | AD14: =+M14+N14 -> 0
A15: =+A14+1 -> 8 | B15: Bodega | C15: AUX03 | D15: Auxiliares de bodega03 | E15: 44896 | F15: =+F14 -> 46022 | G15: =(F15-E15)/365 -> 3.0849315 | H15: 365 | I15: 25 | J15: 35 | K15: 39 | L15: 30 | R15: =+Q15-S15 -> 0 | S15: =IF(Q15>=1200,(1200-Q15),0) -> 0 | Z15: =+U15+V15+W15+X15 -> 0 | AD15: =+M15+N15 -> 0
A16: =+A15+1 -> 9 | B16: Bodega | C16: AUX04 | D16: Auxiliares de bodega04 | E16: 43815 | F16: =+F15 -> 46022 | G16: =(F16-E16)/365 -> 6.0465753 | H16: 415 | I16: 12 | J16: 20 | K16: 39 | L16: 30 | R16: =+Q16-S16 -> 0 | S16: =IF(Q16>=1200,(1200-Q16),0) -> 0 | Z16: =+U16+V16+W16+X16 -> 0 | AD16: =+M16+N16 -> 0
A17: =+A16+1 -> 10 | B17: Bodega | C17: MONT | D17: Montacarguista | E17: 43435 | F17: =+F12 -> 46022 | G17: =(F17-E17)/365 -> 7.0876712 | H17: 450 | I17: 19 | J17: 25 | K17: =39*4 -> 156 | L17: 30 | R17: =+Q17-S17 -> 0 | S17: =IF(Q17>=1200,(1200-Q17),0) -> 0 | Z17: =+U17+V17+W17+X17 -> 0 | AD17: =+M17+N17 -> 0
A18: =+A17+1 -> 11 | B18: Bodega | C18: REV | D18: Revisador | E18: 45170 | F18: =+F13 -> 46022 | G18: =(F18-E18)/365 -> 2.3342466 | H18: 425 | I18: 44 | J18: 33 | K18: 0 | L18: 30 | R18: =+Q18-S18 -> 0 | S18: =IF(Q18>=1200,(1200-Q18),0) -> 0 | Z18: =+U18+V18+W18+X18 -> 0 | AD18: =+M18+N18 -> 0
G19: SUB-TOTAL | H19: =SUM(H12:H18) -> 3130 | M19: =SUM(M12:M18) -> 0 | N19: =SUM(N12:N18) -> 0 | O19: =SUM(O12:O18) -> 0 | P19: =SUM(P12:P18) -> 0 | Q19: =SUM(Q12:Q18) -> 0 | R19: =SUM(R12:R18) -> 0 | S19: =SUM(S12:S18) -> 0 | T19: =SUM(T12:T18) -> 0 | ... Z19: =SUM(Z12:Z18) -> 0 | AD19: =+M19+N19 -> 0
G20: TOTAL | H20: =+H11+H19 -> 7080 | M20: =+M11+M19 -> 0 | N20: =+N11+N19 -> 0 | O20: =+O11+O19 -> 0 | P20: =+P11+P19 -> 0 | Q20: =+Q11+Q19 -> 0 | R20: =+R11+R19 -> 0 | S20: =+S11+S19 -> 0 | T20: =+T11+T19 -> 0 | ... Z20: =+Z11+Z19 -> 0 | AD20: =+M20+N20 -> 0

Sheet Boleta de pago
F1: XYZ S.A. de C.V. 98 Avenida norte , N° 13420, Colonia Escalón, San Salvador, EL Salvador Tel. (503) 4444-6474; FAX: (503) 4444-6436 email: XYZ@gmail.com
A3: Boleta de pago
B4: Período del xx al xx mes de 2024
A6: Código | C6: Nombre | H6: NIT
A7: MONT | C7: =INDEX(PLANILLA!$D$7:$D$18,MATCH($A$7,PLANILLA!$C$7:$C$18,0)) -> Montacarguista | H7: 0614-040483-129-5
A9: Días trabajados: | D9: 30
A11: (+) Ingresos percibidos | H11: (-) Egresos y deducciones
A13: Salario devengado: | D13: =SUMIF(PLANILLA!$C$7:$C$18,$A$7,PLANILLA!$H$7:$H$18) -> 450 | H13: ISSS: | K13: =SUMIF(PLANILLA!$C$7:$C$18,$A$7,PLANILLA!$V$7:$V$18) -> 0
A14: Horas extras: | D14: =SUMIF(PLANILLA!$C$7:$C$18,$A$7,PLANILLA!$AD$7:$AD$18) -> 0 | H14: AFP´S: | K14: =SUMIF(PLANILLA!$C$7:$C$18,$A$7,PLANILLA!$X$7:$X$18) -> 0
A15: Nocturnidad | D15: =SUMIF(PLANILLA!$C$7:$C$18,$A$7,PLANILLA!$O$7:$O$18) -> 0 | H15: FSPV: | K15: 0
A16: Aguinaldo: | D16: =SUMIF(PLANILLA!$C$7:$C$18,$A$7,PLANILLA!$R$7:$R$18) -> 0 | H16: Imp. Sobre / renta: | K16: 0
A17: Bonificaciones: | D17: 0 | H17: Anticipos: | K17: 0
A18: Vacación deveng.: | D18: 0 | H18: Prestamos: | I18: Prestamos | J18: Prestamos | K18: 0
A19: Vacación 30%: | D19: =SUMIF(PLANILLA!$C$7:$C$18,$A$7,PLANILLA!$P$7:$P$18) -> 0 | H19: Otros descuentos: | I19: Otros | J19: Otros | K19: 0
A20: Viáticos: | D20: =SUMIF(PLANILLA!$C$7:$C$18,$A$7,PLANILLA!$L$7:$L$18) -> 30 | H20: Prestamos bancarios: | K20: 0
A21: Premios: | D21: 0 | H21: Seguros: | K21: 0
A22: Dietas | D22: 0 | H22: Descuentos p/equipo: | K22: 0
A23: Otros ingresos: | D23: 0 | H23: Liquidación: | K23: 0
A25: Total ingresos | D25: =SUM(D13:E23) -> 480 | H25: Total egresos | K25: =SUM(K13:L23) -> 0
A27: Total Neto a recibir | D27: =+D25-K25 -> 480 | G27: F.
G28: =+IF(A7<>"",$C$7,"") -> Montacarguista
G29: Nombre y firma de recibido
